odoo/addons/l10n_es_aeat_vat_prorrate_asset/README.rst
odoo/addons/l10n_es_aeat_vat_prorrate_asset/__init__.py
odoo/addons/l10n_es_aeat_vat_prorrate_asset/__manifest__.py
odoo/addons/l10n_es_aeat_vat_prorrate_asset/i18n/ca.po
odoo/addons/l10n_es_aeat_vat_prorrate_asset/i18n/cs.po
odoo/addons/l10n_es_aeat_vat_prorrate_asset/i18n/es.po
odoo/addons/l10n_es_aeat_vat_prorrate_asset/i18n/es_CO.po
odoo/addons/l10n_es_aeat_vat_prorrate_asset/i18n/es_CR.po
odoo/addons/l10n_es_aeat_vat_prorrate_asset/i18n/fr.po
odoo/addons/l10n_es_aeat_vat_prorrate_asset/i18n/gl.po
odoo/addons/l10n_es_aeat_vat_prorrate_asset/i18n/hr.po
odoo/addons/l10n_es_aeat_vat_prorrate_asset/i18n/l10n_es_aeat_vat_prorrate_asset.pot
odoo/addons/l10n_es_aeat_vat_prorrate_asset/i18n/nl.po
odoo/addons/l10n_es_aeat_vat_prorrate_asset/i18n/pl.po
odoo/addons/l10n_es_aeat_vat_prorrate_asset/i18n/pt.po
odoo/addons/l10n_es_aeat_vat_prorrate_asset/i18n/pt_BR.po
odoo/addons/l10n_es_aeat_vat_prorrate_asset/i18n/ru.po
odoo/addons/l10n_es_aeat_vat_prorrate_asset/i18n/sl.po
odoo/addons/l10n_es_aeat_vat_prorrate_asset/i18n/sv.po
odoo/addons/l10n_es_aeat_vat_prorrate_asset/i18n/tr.po
odoo/addons/l10n_es_aeat_vat_prorrate_asset/i18n/vi.po
odoo/addons/l10n_es_aeat_vat_prorrate_asset/migrations/13.0.1.0.0/post-migration.py
odoo/addons/l10n_es_aeat_vat_prorrate_asset/models/__init__.py
odoo/addons/l10n_es_aeat_vat_prorrate_asset/models/account_asset.py
odoo/addons/l10n_es_aeat_vat_prorrate_asset/models/account_move.py
odoo/addons/l10n_es_aeat_vat_prorrate_asset/models/mod303.py
odoo/addons/l10n_es_aeat_vat_prorrate_asset/readme/CONTRIBUTORS.rst
odoo/addons/l10n_es_aeat_vat_prorrate_asset/readme/DESCRIPTION.rst
odoo/addons/l10n_es_aeat_vat_prorrate_asset/readme/ROADMAP.rst
odoo/addons/l10n_es_aeat_vat_prorrate_asset/readme/USAGE.rst
odoo/addons/l10n_es_aeat_vat_prorrate_asset/static/description/icon.png
odoo/addons/l10n_es_aeat_vat_prorrate_asset/static/description/icon_source.svg
odoo13_addon_l10n_es_aeat_vat_prorrate_asset-13.0.1.0.1.dev5.dist-info/METADATA
odoo13_addon_l10n_es_aeat_vat_prorrate_asset-13.0.1.0.1.dev5.dist-info/WHEEL
odoo13_addon_l10n_es_aeat_vat_prorrate_asset-13.0.1.0.1.dev5.dist-info/top_level.txt
odoo13_addon_l10n_es_aeat_vat_prorrate_asset-13.0.1.0.1.dev5.dist-info/RECORD
