Metadata-Version: 2.1
Name: odoo13-addon-l10n-es-aeat-vat-prorrate-asset
Version: 13.0.1.0.1.dev5
Summary: AEAT - Prorrata de IVA - Extensión para los activos
Home-page: https://github.com/OCA/l10n-spain
Author: Tecnativa, Odoo Community Association (OCA)
Author-email: support@odoo-community.org
License: AGPL-3
Platform: UNKNOWN
Classifier: Programming Language :: Python
Classifier: Framework :: Odoo
Classifier: Framework :: Odoo :: 13.0
Classifier: License :: OSI Approved :: GNU Affero General Public License v3
Requires-Python: >=3.5
Requires-Dist: odoo13-addon-account-asset-management
Requires-Dist: odoo13-addon-l10n-es-aeat-vat-prorrate
Requires-Dist: odoo <13.1dev,>=13.0a
